{
  "generated_at": "2026-07-16 07:39 KST",
  "note": "산업별 선행지표(월간·주간·분기). 색상은 과열도가 아니라 업황 방향성(모멘텀)을 의미합니다. 유료 원지표는 수동 입력 또는 공개 대체지표로 처리합니다.",
  "indicators": [
    {
      "name": "반도체·전자부품 생산자물가(PPI)",
      "category": "반도체",
      "freq": "월간",
      "value_text": "72.7",
      "date": "2026-06-01",
      "change_text": "전월 -0.4% · 전년 +26.1%",
      "state": "확장",
      "signal_level": 0,
      "comment": "반도체·전자부품 출하가격 방향. 상승은 가격 강세(제조사에 우호적)를 시사합니다. 카드 색상은 과열도가 아니라 전년동월대비 방향(모멘텀)을 나타냅니다. 최신값 72.7 (지수), 전월 -0.4%, 전년 +26.1%.",
      "mdd_line": "",
      "source": "FRED:PCU33443344",
      "ok": true,
      "chart": {
        "type": "value",
        "unit": "지수",
        "labels": [
          "2023-07-01",
          "2023-08-01",
          "2023-09-01",
          "2023-10-01",
          "2023-11-01",
          "2023-12-01",
          "2024-01-01",
          "2024-02-01",
          "2024-03-01",
          "2024-04-01",
          "2024-05-01",
          "2024-06-01",
          "2024-07-01",
          "2024-08-01",
          "2024-09-01",
          "2024-10-01",
          "2024-11-01",
          "2024-12-01",
          "2025-01-01",
          "2025-02-01",
          "2025-03-01",
          "2025-04-01",
          "2025-05-01",
          "2025-06-01",
          "2025-07-01",
          "2025-08-01",
          "2025-09-01",
          "2025-10-01",
          "2025-11-01",
          "2025-12-01",
          "2026-01-01",
          "2026-02-01",
          "2026-03-01",
          "2026-04-01",
          "2026-05-01",
          "2026-06-01"
        ],
        "series": {
          "value": [
            56.919,
            57.125,
            57.362,
            57.374,
            57.591,
            57.536,
            57.873,
            58.044,
            58.094,
            58.245,
            58.195,
            58.052,
            57.453,
            57.484,
            57.533,
            57.992,
            58.925,
            58.817,
            58.261,
            58.059,
            58.414,
            58.312,
            58.318,
            57.596,
            57.566,
            59.626,
            59.754,
            60.114,
            60.857,
            61.052,
            61.572,
            67.007,
            68.261,
            73.281,
            72.96,
            72.656
          ]
        }
      }
    },
    {
      "name": "반도체·전자부품 산업생산지수",
      "category": "반도체",
      "freq": "월간",
      "value_text": "188.0",
      "date": "2026-05-01",
      "change_text": "전월 +2.4% · 전년 +14.4%",
      "state": "확장",
      "signal_level": 0,
      "comment": "반도체·전자부품 생산 활동 수준. 상승은 가동·출하 확대를 시사합니다. 카드 색상은 과열도가 아니라 전년동월대비 방향(모멘텀)을 나타냅니다. 최신값 188.0 (지수), 전월 +2.4%, 전년 +14.4%.",
      "mdd_line": "",
      "source": "FRED:IPG3344S",
      "ok": true,
      "chart": {
        "type": "value",
        "unit": "지수",
        "labels": [
          "2023-06-01",
          "2023-07-01",
          "2023-08-01",
          "2023-09-01",
          "2023-10-01",
          "2023-11-01",
          "2023-12-01",
          "2024-01-01",
          "2024-02-01",
          "2024-03-01",
          "2024-04-01",
          "2024-05-01",
          "2024-06-01",
          "2024-07-01",
          "2024-08-01",
          "2024-09-01",
          "2024-10-01",
          "2024-11-01",
          "2024-12-01",
          "2025-01-01",
          "2025-02-01",
          "2025-03-01",
          "2025-04-01",
          "2025-05-01",
          "2025-06-01",
          "2025-07-01",
          "2025-08-01",
          "2025-09-01",
          "2025-10-01",
          "2025-11-01",
          "2025-12-01",
          "2026-01-01",
          "2026-02-01",
          "2026-03-01",
          "2026-04-01",
          "2026-05-01"
        ],
        "series": {
          "value": [
            135.4366,
            136.6894,
            135.6233,
            134.4233,
            136.4045,
            137.8263,
            138.9374,
            139.4212,
            138.2248,
            138.3547,
            143.8737,
            144.2792,
            143.4192,
            143.4068,
            148.7946,
            146.4195,
            148.7125,
            148.1992,
            150.2275,
            158.0732,
            159.6876,
            159.2281,
            162.2271,
            164.3526,
            163.1741,
            171.5555,
            169.197,
            165.667,
            169.1163,
            169.7424,
            170.5402,
            176.8583,
            176.0916,
            178.5672,
            183.6088,
            188.0105
          ]
        }
      }
    },
    {
      "name": "컴퓨터·전자제품 신규주문",
      "category": "반도체",
      "freq": "월간",
      "value_text": "29,883.0",
      "date": "2026-05-01",
      "change_text": "전월 +0.2% · 전년 +13.2%",
      "state": "확장",
      "signal_level": 0,
      "comment": "수요 선행지표. 반도체 단독 주문은 FRED에 없어 상위 범주(컴퓨터·전자제품)로 대체합니다. 카드 색상은 과열도가 아니라 전년동월대비 방향(모멘텀)을 나타냅니다. 최신값 29,883.0 (백만 달러), 전월 +0.2%, 전년 +13.2%.",
      "mdd_line": "",
      "source": "FRED:A34SNO",
      "ok": true,
      "chart": {
        "type": "value",
        "unit": "백만 달러",
        "labels": [
          "2023-06-01",
          "2023-07-01",
          "2023-08-01",
          "2023-09-01",
          "2023-10-01",
          "2023-11-01",
          "2023-12-01",
          "2024-01-01",
          "2024-02-01",
          "2024-03-01",
          "2024-04-01",
          "2024-05-01",
          "2024-06-01",
          "2024-07-01",
          "2024-08-01",
          "2024-09-01",
          "2024-10-01",
          "2024-11-01",
          "2024-12-01",
          "2025-01-01",
          "2025-02-01",
          "2025-03-01",
          "2025-04-01",
          "2025-05-01",
          "2025-06-01",
          "2025-07-01",
          "2025-08-01",
          "2025-09-01",
          "2025-10-01",
          "2025-11-01",
          "2025-12-01",
          "2026-01-01",
          "2026-02-01",
          "2026-03-01",
          "2026-04-01",
          "2026-05-01"
        ],
        "series": {
          "value": [
            24640.0,
            24778.0,
            24949.0,
            25148.0,
            25316.0,
            25423.0,
            25075.0,
            25527.0,
            25258.0,
            25104.0,
            25247.0,
            25269.0,
            25253.0,
            25551.0,
            25580.0,
            25755.0,
            25716.0,
            25550.0,
            25946.0,
            26138.0,
            26187.0,
            25733.0,
            25858.0,
            26397.0,
            26639.0,
            26786.0,
            26485.0,
            26803.0,
            26863.0,
            27015.0,
            27945.0,
            28163.0,
            28559.0,
            29926.0,
            29813.0,
            29883.0
          ]
        }
      }
    },
    {
      "name": "빅테크 CAPEX",
      "category": "반도체",
      "freq": "분기",
      "value_text": "$175.8B",
      "date": "2026Q3",
      "change_text": "전년 +197.0% · MSFT/GOOGL/AMZN/META/ORCL 합산",
      "state": "확장",
      "signal_level": 0,
      "comment": "AI 데이터센터 투자 수요를 보는 반도체 선행지표입니다. SEC companyfacts의 유형자산 취득 지출을 주요 빅테크 기준으로 합산했습니다.",
      "mdd_line": "",
      "source": "SEC EDGAR companyfacts",
      "ok": true,
      "chart": null
    },
    {
      "name": "HD한국조선해양 수주",
      "category": "조선",
      "freq": "주간",
      "value_text": "13건 / 약 8.14조원",
      "date": "2026-07-16",
      "change_text": "최근 90일 수주 관련 공시 · 최근: 단일판매ㆍ공급계약체결(자회사의 주요경영사항)           ",
      "state": "수주 활발",
      "signal_level": 0,
      "comment": "DART 공시명에 '단일판매/공급계약/수주'가 포함된 신규 공시를 집계합니다. 가능한 경우 공시 원문에서 계약금액(원)을 정규식으로 추출해 합산합니다. 정정공시·자회사 연결 여부·통화 환산은 후속 검증이 필요하므로, 수주잔고의 방향을 보는 보조지표로 사용하세요.",
      "mdd_line": "",
      "source": "DART:009540",
      "ok": true,
      "chart": null
    },
    {
      "name": "HD현대중공업 수주",
      "category": "조선",
      "freq": "주간",
      "value_text": "12건 / 약 7.14조원",
      "date": "2026-07-16",
      "change_text": "최근 90일 수주 관련 공시 · 최근: 단일판매ㆍ공급계약체결              ",
      "state": "수주 활발",
      "signal_level": 0,
      "comment": "DART 공시명에 '단일판매/공급계약/수주'가 포함된 신규 공시를 집계합니다. 가능한 경우 공시 원문에서 계약금액(원)을 정규식으로 추출해 합산합니다. 정정공시·자회사 연결 여부·통화 환산은 후속 검증이 필요하므로, 수주잔고의 방향을 보는 보조지표로 사용하세요.",
      "mdd_line": "",
      "source": "DART:329180",
      "ok": true,
      "chart": null
    },
    {
      "name": "삼성중공업 수주",
      "category": "조선",
      "freq": "주간",
      "value_text": "11건 / 약 10.05조원",
      "date": "2026-07-16",
      "change_text": "최근 90일 수주 관련 공시 · 최근: 단일판매ㆍ공급계약체결              ",
      "state": "수주 활발",
      "signal_level": 0,
      "comment": "DART 공시명에 '단일판매/공급계약/수주'가 포함된 신규 공시를 집계합니다. 가능한 경우 공시 원문에서 계약금액(원)을 정규식으로 추출해 합산합니다. 정정공시·자회사 연결 여부·통화 환산은 후속 검증이 필요하므로, 수주잔고의 방향을 보는 보조지표로 사용하세요.",
      "mdd_line": "",
      "source": "DART:010140",
      "ok": true,
      "chart": null
    },
    {
      "name": "한화오션 수주",
      "category": "조선",
      "freq": "주간",
      "value_text": "5건 / 약 2.44조원",
      "date": "2026-07-16",
      "change_text": "최근 90일 수주 관련 공시 · 최근: 단일판매ㆍ공급계약체결              ",
      "state": "수주 활발",
      "signal_level": 0,
      "comment": "DART 공시명에 '단일판매/공급계약/수주'가 포함된 신규 공시를 집계합니다. 가능한 경우 공시 원문에서 계약금액(원)을 정규식으로 추출해 합산합니다. 정정공시·자회사 연결 여부·통화 환산은 후속 검증이 필요하므로, 수주잔고의 방향을 보는 보조지표로 사용하세요.",
      "mdd_line": "",
      "source": "DART:042660",
      "ok": true,
      "chart": null
    },
    {
      "name": "미국 소프트웨어 대형주 매출 성장률",
      "category": "소프트웨어",
      "freq": "분기",
      "value_text": "+124.9%",
      "date": "2026Q3",
      "change_text": "대상: MSFT, ORCL, CRM, NOW, ADBE, PLTR",
      "state": "확장",
      "signal_level": 0,
      "comment": "SEC companyfacts에서 주요 소프트웨어 기업의 분기 매출 전년동기 대비 성장률을 계산한 평균입니다. 기업별 회계연도와 태그 차이 때문에 방향성 지표로 사용하세요.",
      "mdd_line": "",
      "source": "SEC EDGAR companyfacts",
      "ok": true,
      "chart": null
    },
    {
      "name": "미국 소프트웨어 대형주 영업이익률",
      "category": "소프트웨어",
      "freq": "분기",
      "value_text": "32.0%",
      "date": "2026Q3",
      "change_text": "FCF margin 평균 29.2%",
      "state": "고수익",
      "signal_level": 0,
      "comment": "성장주의 질을 확인하는 지표입니다. 매출 성장률이 높아도 영업이익률과 FCF margin이 훼손되면 업황의 질은 낮게 봅니다.",
      "mdd_line": "",
      "source": "SEC EDGAR companyfacts",
      "ok": true,
      "chart": null
    },
    {
      "name": "미국 소프트웨어 RPO 성장률",
      "category": "소프트웨어",
      "freq": "분기",
      "value_text": "+101.4%",
      "date": "2026Q3",
      "change_text": "RPO 공개·태그 식별 가능 기업 평균",
      "state": "확장",
      "signal_level": 0,
      "comment": "Remaining Performance Obligation은 앞으로 매출로 인식될 계약 잔고입니다. 공개·XBRL 태그가 가능한 기업만 평균에 포함됩니다.",
      "mdd_line": "",
      "source": "SEC EDGAR companyfacts",
      "ok": true,
      "chart": null
    }
  ]
}
